decorators/__init__.py
middlewares/__init__.py
py_cas/CAS.py
py_cas/Models.py
py_cas/__init__.py
py_cas-0.3.1.dist-info/METADATA
py_cas-0.3.1.dist-info/WHEEL
py_cas-0.3.1.dist-info/top_level.txt
py_cas-0.3.1.dist-info/RECORD
