Metadata-Version: 2.1
Name: py-cas
Version: 0.3.1
Summary: python client of c.a.s
Home-page: UNKNOWN
Author: includeamin
Author-email: includeamin@gmail.com
License: UNKNOWN
Platform: UNKNOWN
Classifier: Programming Language :: Python :: 3
Classifier: License :: OSI Approved :: MIT License
Classifier: Operating System :: OS Independent
Requires-Python: >=3.6
